README.txt
setup.py
Unipath.egg-info/PKG-INFO
Unipath.egg-info/SOURCES.txt
Unipath.egg-info/dependency_links.txt
Unipath.egg-info/top_level.txt
unipath/__init__.py
unipath/abstractpath.py
unipath/errors.py
unipath/path.py
unipath/test.py
unipath/tools.py
