Metadata-Version: 1.0
Name: Unipath
Version: 0.2.1
Summary: Object-oriented alternative to os/os.path/shutil
Home-page: http://sluggo.scrapping.cc/python/unipath/
Author: Mike Orr
Author-email: sluggoster@gmail.com
License: Python
Download-URL: http://sluggo.scrapping.cc/python/unipath/Unipath-0.2.1.tar.gz
Keywords: os.path filename pathspec path files directories filesystem
Platform: UNKNOWN
Classifier: License :: OSI Approved :: Python Software Foundation License
Classifier: Operating System :: OS Independent
Classifier: Topic :: Software Development :: Libraries :: Python Modules
Classifier: Topic :: Utilities
